sfdevtools/__init__.py
sfdevtools/app/__init__.py
sfdevtools/app/main.py
sfdevtools/data_cache/DCache.py
sfdevtools/data_cache/DCacheManager.py
sfdevtools/data_cache/DComponents.py
sfdevtools/data_cache/DConverter.py
sfdevtools/data_cache/DOrderCache.py
sfdevtools/data_cache/DPage.py
sfdevtools/data_cache/DStrategy.py
sfdevtools/data_cache/DTimelyCache.py
sfdevtools/data_cache/DurationMapper/DurationEle.py
sfdevtools/data_cache/DurationMapper/DurationSearcher.py
sfdevtools/data_cache/DurationMapper/__init__.py
sfdevtools/data_cache/__init__.py
sfdevtools/data_control/TSBackgroundCtrl.py
sfdevtools/data_control/TSDataCtrl.py
sfdevtools/data_control/TSDataCtrl_pub.py
sfdevtools/data_control/TSDataCtrl_sub.py
sfdevtools/data_control/TSDataManager.py
sfdevtools/data_control/__init__.py
sfdevtools/devTools/AtomicData.py
sfdevtools/devTools/DatetimeTools.py
sfdevtools/devTools/DiscontinueSeelp.py
sfdevtools/devTools/FuncFifoQ.py
sfdevtools/devTools/HDTimer.py
sfdevtools/devTools/MsgQ.py
sfdevtools/devTools/SafeDict.py
sfdevtools/devTools/SingletonDoubleChecked.py
sfdevtools/devTools/ThreadClass.py
sfdevtools/devTools/ThreadQ.py
sfdevtools/devTools/__init__.py
sfdevtools/grpc_protos/cop_tools.py
sfdevtools/grpc_protos/eagle.proto
sfdevtools/grpc_protos/eagle_pb2.py
sfdevtools/grpc_protos/eagle_pb2_grpc.py
sfdevtools/grpc_protos/falcon.proto
sfdevtools/grpc_protos/falcon_pb2.py
sfdevtools/grpc_protos/falcon_pb2_grpc.py
sfdevtools/grpc_protos/magpie.proto
sfdevtools/grpc_protos/magpie_pb2.py
sfdevtools/grpc_protos/magpie_pb2_grpc.py
sfdevtools/grpc_protos/peacock.proto
sfdevtools/grpc_protos/peacock_pb2.py
sfdevtools/grpc_protos/peacock_pb2_grpc.py
sfdevtools/grpc_protos/python_showcases.proto
sfdevtools/grpc_protos/python_showcases_pb2.py
sfdevtools/grpc_protos/python_showcases_pb2_grpc.py
sfdevtools/grpc_protos/ts_cop.proto
sfdevtools/grpc_protos/ts_cop_pb2.py
sfdevtools/grpc_protos/ts_cop_pb2_grpc.py
sfdevtools/grpc_protos/tweety.proto
sfdevtools-1.76.0.dist-info/WHEEL
sfdevtools-1.76.0.dist-info/METADATA
sfdevtools-1.76.0.dist-info/RECORD
