Metadata-Version: 2.1
Name: sfdevtools
Version: 1.76.0
Summary: 
Author: SulfredLee
Author-email: sflee1112@gmail.com
Requires-Python: >=3.8,<4.0
Classifier: Programming Language :: Python :: 3
Classifier: Programming Language :: Python :: 3.8
Classifier: Programming Language :: Python :: 3.9
Classifier: Programming Language :: Python :: 3.10
Classifier: Programming Language :: Python :: 3.11
Requires-Dist: boto3 (>=1.26.61,<2.0.0)
Requires-Dist: grpcio (==1.54.0)
Requires-Dist: grpcio-tools (==1.54.0)
Requires-Dist: nanoid (>=2.0.0,<3.0.0)
Requires-Dist: pandas (>=1.5.3,<2.0.0)
Requires-Dist: psycopg2-binary (>=2.9.5,<3.0.0)
Requires-Dist: pyzmq (==24.0.1)
Requires-Dist: sqlalchemy (>=2.0.3,<3.0.0)
